{"objects":[{"object_name":"Bookshelf","spatial_relationship_with_user":"center of the image"},{"object_name":"Book A","spatial_relationship_with_user":"on the top shelf of the bookshelf"},{"object_name":"Book B","spatial_relationship_with_user":"on the top shelf of the bookshelf"},{"object_name":"Pencil","spatial_relationship_with_user":"on the top shelf of the bookshelf"},{"object_name":"File Binder","spatial_relationship_with_user":"on the top shelf of the bookshelf"},{"object_name":"Book C","spatial_relationship_with_user":"on the second shelf of the bookshelf"},{"object_name":"Smartphone","spatial_relationship_with_user":"on the second shelf of the bookshelf"},{"object_name":"Books","spatial_relationship_with_user":"right side of the second shelf of the bookshelf"},{"object_name":"Book D","spatial_relationship_with_user":"on the bottom shelf of the bookshelf"}]}